gangaextension/__init__.py
gangaextension/kernelextension/__init__.py
gangaextension/kernelextension/gangajob.py
gangaextension/kernelextension/gangamagic.py
gangaextension/nbextension/cellqueue.js
gangaextension/nbextension/displaymonitor.js
gangaextension/nbextension/extension.js
gangaextension/nbextension/gangamonitor.js
gangaextension/nbextension/joblistbuilder.js
gangaextension/nbextension/load_file.js
gangaextension/nbextension/time.js
gangaextension/nbextension/static/gangaicon.gif
gangaextension/nbextension/static/gangaicon.png
gangaextension/nbextension/static/jobdialog.html
gangaextension/nbextension/static/joblist.html
gangaextension/nbextension/static/joblistrow.html
gangaextension/nbextension/static/jobmonitor.html
gangaextension/nbextension/static/style.css
gangaextension/nbextension/static/treetab.css
gangaextension/serverextension/__init__.py
gangaextension/serverextension/serverextension.py
gangaextension/serverextension/swanhandler.py
gangaextension-0.0.1.dist-info/DESCRIPTION.rst
gangaextension-0.0.1.dist-info/METADATA
gangaextension-0.0.1.dist-info/RECORD
gangaextension-0.0.1.dist-info/WHEEL
gangaextension-0.0.1.dist-info/metadata.json
gangaextension-0.0.1.dist-info/top_level.txt
