Metadata-Version: 2.0
Name: gangaextension
Version: 0.0.1
Summary: Ganga Extension for Jupyter Notebook
Home-page: https://github.com/apsknight/gangaextension
Author: Aman Pratap Singh
Author-email: amanprtpsingh@gmail.com
License: UNKNOWN
Platform: UNKNOWN
